Metadata-Version: 2.4
Name: mongo_datatables
Version: 1.1.2
Summary: Server-side processing for DataTables and Editor with MongoDB
Home-page: https://github.com/pjosols/mongo-datatables
Author: Paul Olsen
Author-email: pjosols@wholeshoot.com
License: MIT
Project-URL: Bug Reports, https://github.com/pjosols/mongo-datatables/issues
Project-URL: Source, https://github.com/pjosols/mongo-datatables
Project-URL: Documentation, https://github.com/pjosols/mongo-datatables#readme
Keywords: datatables editor mongodb pymongo flask django server-side
Classifier: Development Status :: 5 - Production/Stable
Classifier: Intended Audience :: Developers
Classifier: License :: OSI Approved :: MIT License
Classifier: Programming Language :: Python :: 3.8
Classifier: Programming Language :: Python :: 3.9
Classifier: Programming Language :: Python :: 3.10
Classifier: Programming Language :: Python :: 3.11
Classifier: Programming Language :: Python :: 3.12
Classifier: Programming Language :: Python :: 3.13
Classifier: Topic :: Database
Classifier: Topic :: Software Development :: Libraries :: Python Modules
Classifier: Framework :: Flask
Classifier: Framework :: Django
Requires-Python: >=3.8
License-File: LICENSE.txt
Requires-Dist: pymongo>=3.9.0
Provides-Extra: dev
Requires-Dist: pytest; extra == "dev"
Requires-Dist: pytest-cov; extra == "dev"
Requires-Dist: coverage; extra == "dev"
Requires-Dist: tox; extra == "dev"
Requires-Dist: sphinx; extra == "dev"
Requires-Dist: sphinx_rtd_theme; extra == "dev"
Provides-Extra: test
Requires-Dist: pytest; extra == "test"
Requires-Dist: pytest-cov; extra == "test"
Requires-Dist: coverage; extra == "test"
Provides-Extra: docs
Requires-Dist: sphinx; extra == "docs"
Requires-Dist: sphinx-rtd-theme; extra == "docs"
Dynamic: author
Dynamic: author-email
Dynamic: classifier
Dynamic: description
Dynamic: description-content-type
Dynamic: home-page
Dynamic: keywords
Dynamic: license
Dynamic: license-file
Dynamic: project-url
Dynamic: provides-extra
Dynamic: requires-dist
Dynamic: requires-python
Dynamic: summary
